nspd_request/__init__.py
nspd_request/nspd_request.py
nspd_request/utils.py
nspd_request/version.py
nspd_request-2.0.0.dist-info/licenses/LICENSE
nspd_request-2.0.0.dist-info/METADATA
nspd_request-2.0.0.dist-info/WHEEL
nspd_request-2.0.0.dist-info/top_level.txt
nspd_request-2.0.0.dist-info/RECORD
