Metadata-Version: 2.4
Name: nspd-request
Version: 2.0.0
Summary: Python-библиотека для работы с НСПД (Национальная система пространственных данных)
Home-page: https://github.com/Logar1t/NSPD-request
Author: Logar1t
Author-email: Logar1t <logar1t.official@gmail.com>
Maintainer-email: Logar1t <logar1t.official@gmail.com>
License: MIT
Project-URL: Homepage, https://github.com/Logar1t/NSPD-request
Project-URL: Repository, https://github.com/Logar1t/NSPD-request
Project-URL: Issues, https://github.com/Logar1t/NSPD-request/issues
Project-URL: README, https://github.com/Logar1t/NSPD-request/blob/main/README.md
Project-URL: Documentation, https://github.com/Logar1t/NSPD-request/blob/main/DOCUMENTATION.md
Keywords: nspd,кадастр,недвижимость,api,росреестр
Classifier: Development Status :: 5 - Production/Stable
Classifier: Intended Audience :: Developers
Classifier: License :: OSI Approved :: MIT License
Classifier: Operating System :: OS Independent
Classifier: Programming Language :: Python :: 3
Classifier: Programming Language :: Python :: 3.8
Classifier: Programming Language :: Python :: 3.9
Classifier: Programming Language :: Python :: 3.10
Classifier: Programming Language :: Python :: 3.11
Classifier: Programming Language :: Python :: 3.12
Classifier: Topic :: Software Development :: Libraries :: Python Modules
Classifier: Topic :: Internet :: WWW/HTTP :: Dynamic Content
Classifier: Topic :: Scientific/Engineering :: GIS
Requires-Python: >=3.8
License-File: LICENSE
Requires-Dist: requests>=2.25.1
Requires-Dist: pyproj>=3.0.0
Requires-Dist: shapely>=2.0.0
Provides-Extra: dev
Requires-Dist: pytest>=6.0; extra == "dev"
Requires-Dist: pytest-cov>=2.0; extra == "dev"
Requires-Dist: black>=21.0; extra == "dev"
Requires-Dist: flake8>=3.8; extra == "dev"
Requires-Dist: mypy>=0.800; extra == "dev"
Dynamic: author
Dynamic: home-page
Dynamic: license-file
Dynamic: requires-python
